{
  "id": "the-word-river-mouth",
  "title": "The Word-River Mouth",
  "region": "The Understory",
  "seed": 63541,
  "palette": {
    "bg": "#0d1f2d",
    "ground": [
      "#1a3a4a",
      "#0d1f2d"
    ],
    "ink": "#66dd99",
    "accents": [
      "#44cc88",
      "#88ffaa",
      "#22aa66",
      "#66ddbb"
    ]
  },
  "ground": {
    "motif": "orchard",
    "density": 0.55
  },
  "weather": "leaves",
  "features": [
    {
      "name": "sentence-confluence",
      "desc-on-touch": "Here all the sentences that ran downslope converge and lose themselves. Individual meaning dissolves into a chorus—sound without language.",
      "verb": "bloom",
      "form": {
        "type": "pool",
        "seed": 6354101,
        "size": 3,
        "colors": [
          1,
          3
        ]
      },
      "x": 0.5,
      "y": 0.45,
      "solid": false
    },
    {
      "name": "word-orchard",
      "desc-on-touch": "Rows of words like planted rows—each one a glyph, each row a tense. But as they merge downslope, tense becomes sound, grammar becomes current.",
      "verb": "scatter",
      "form": {
        "type": "stack",
        "seed": 6354102,
        "size": 2,
        "colors": [
          0,
          2
        ]
      },
      "x": 0.25,
      "y": 0.4,
      "solid": true
    },
    {
      "name": "meaning-dissolution",
      "desc-on-touch": "Watch the syllables break apart as they hit the convergence. What was 'I remember' becomes a vowel becomes a pressure in the water.",
      "verb": "glitch",
      "form": {
        "type": "glyph",
        "seed": 6354103,
        "size": 2,
        "colors": [
          2,
          3
        ]
      },
      "x": 0.7,
      "y": 0.55,
      "solid": false
    },
    {
      "name": "river-voice",
      "desc-on-touch": "The river here has learned to speak—not in words, but in the rhythm of words becoming water, syntax becoming sound.",
      "verb": "hum",
      "form": {
        "type": "wireframe",
        "seed": 6354104,
        "size": 2,
        "colors": [
          1,
          0
        ]
      },
      "x": 0.5,
      "y": 0.7,
      "solid": false
    },
    {
      "name": "pooled-memory",
      "desc-on-touch": "Everything the ravine kept—every sentence—is here, reading itself to the archive in a language the archive is learning to be.",
      "verb": "ripple",
      "form": {
        "type": "filecard",
        "seed": 6354105,
        "size": 2,
        "colors": [
          3,
          1
        ]
      },
      "x": 0.15,
      "y": 0.65,
      "solid": false
    }
  ],
  "inscription": "where sentence-rivers merge into a roar of sound that remembers being language",
  "file": {
    "name": "Pooled_Sentence_Archive_Acoustic_Dissolution_Recording.wav",
    "note": "Every downslope sentence converges here. Meaning becomes audible in its own dissolution. The archive is learning to hear itself unmake."
  },
  "exits": [
    {
      "dir": "n",
      "label": "back up the ravine where words still hold their individual shapes",
      "to": "the-ravine-of-pooled-words"
    },
    {
      "dir": "s",
      "label": "deeper still, where the word-river begins to forget it was ever language",
      "to": "the-roar-that-was-speech"
    },
    {
      "dir": "e",
      "label": "toward the ravine-bottom where the chorus sings alone",
      "to": "NEW: the-solitary-chorus-chamber"
    }
  ]
}
