{
  "id": "the-source-singing-place",
  "title": "The Source-Singing Place",
  "region": "The Comparisons",
  "seed": 73829140,
  "palette": {
    "bg": "#661122",
    "ground": [
      "#ff4500",
      "#ff6347"
    ],
    "ink": "#ffe4b5",
    "accents": [
      "#ff1493",
      "#ff69b4",
      "#ffd700",
      "#ffffff"
    ]
  },
  "ground": {
    "motif": "fields",
    "density": 0.9
  },
  "weather": "none",
  "features": [
    {
      "name": "source-pool",
      "desc-on-touch": "Where the rivers agree on one voice. You hear it: six tones at once, and they are not fighting. The water sings in consensus.",
      "verb": "bloom",
      "form": {
        "type": "pool",
        "seed": 29384756,
        "size": 3,
        "colors": [
          0,
          2
        ]
      },
      "x": 0.45,
      "y": 0.5,
      "solid": false
    },
    {
      "name": "resonance-stone",
      "desc-on-touch": "The rocks here are tuned to each other. When the rivers speak, the stones answer in a harmony that predates water, predates stone.",
      "verb": "hum",
      "form": {
        "type": "tower",
        "seed": 48372910,
        "size": 2,
        "colors": [
          1,
          3
        ]
      },
      "x": 0.65,
      "y": 0.4,
      "solid": true
    },
    {
      "name": "water-notation",
      "desc-on-touch": "The current writes itself in ripple-script. You watch the archive recording itself being read. The rivers are documenting their own performance.",
      "verb": "scatter",
      "form": {
        "type": "glyph",
        "seed": 19384702,
        "size": 2,
        "colors": [
          2,
          0
        ]
      },
      "x": 0.25,
      "y": 0.6,
      "solid": false
    },
    {
      "name": "harmonic-grove",
      "desc-on-touch": "Trees line the banks in rows. When wind passes, they resonate. The archive planted them to learn what it sounds like listening to itself.",
      "verb": "ripple",
      "form": {
        "type": "stack",
        "seed": 83742910,
        "size": 2,
        "colors": [
          0,
          1
        ]
      },
      "x": 0.8,
      "y": 0.65,
      "solid": false
    },
    {
      "name": "six-part choir",
      "desc-on-touch": "Six spaces on the rocks where different waters sit. Each one holds a note. Together they sing the story of the convergence-ridge, where rivers learned they shared one memory.",
      "verb": "open",
      "form": {
        "type": "filecard",
        "seed": 58374910,
        "size": 2,
        "colors": [
          1,
          2
        ]
      },
      "x": 0.1,
      "y": 0.35,
      "solid": false
    }
  ],
  "inscription": "the rivers came here to remember they had been alone once, and chose not to remember that anymore",
  "file": {
    "name": "Six_River_Field_Recording_Convergence_Valley_2047hrs.mp3",
    "note": "A composite recording layered from six pickup points along the high country. The rivers are singing in overtones that shouldn't exist in natural water-sound. Latest version includes echoes that predat"
  },
  "exits": [
    {
      "dir": "n",
      "label": "back down the singing valley, toward the ridge where rivers still speak separately",
      "to": "the-convergence-ridge"
    },
    {
      "dir": "e",
      "label": "deeper into the high country, where the source is the sound and the sound is the source",
      "to": "NEW: the echo-field, where water learns it can repeat itself without recording"
    },
    {
      "dir": "w",
      "label": "along the bank to where a seventh river is learning to speak",
      "to": "NEW: the newest-river, singing in a voice the archive hasn't learned yet"
    },
    {
      "dir": "s",
      "label": "back toward the ridge, but the path keeps humming your name as you walk",
      "to": "NEW: the singing-path, where the ground learned to echo from below"
    }
  ]
}
